{
  "jmccann": {
    "name": "Joe McCann",
    "avatar": "https://pbs.twimg.com/profile_images/846386052910637056/tWGT0XAz_400x400.jpg",
    "email": null,
    "homepage": null,
    "twitter": "joemccann",
    "github": "joemccann",
    "linkedin": null,
    "status": "emeriti"
  },
  "asexton": {
    "name": "Alex Sexton",
    "avatar": "https://pbs.twimg.com/profile_images/1034325028026769408/hz_G2I3L_400x400.jpg",
    "email": null,
    "homepage": null,
    "twitter": "slexaxton",
    "github": "slexaxton",
    "linkedin": null,
    "status": "emeriti"
  },
  "rmurphey": {
    "name": "Rebecca Murphey",
    "avatar": "https://pbs.twimg.com/profile_images/1259973234398769154/uNcYGdTr_400x400.jpg",
    "email-archived": "rmurphey@gmail.com",
    "homepage": null,
    "twitter": "rmurphey",
    "github": "rmurphey",
    "linkedin": null,
    "status": "emeriti"
  },
  "lingram": {
    "name": "Lon Ingram",
    "avatar": "https://pbs.twimg.com/profile_images/970161690233864192/rztEhZFR_400x400.jpg",
    "email-archived": "lawnsea@gmail.com",
    "homepage": null,
    "twitter": "lawnsea",
    "github": "lawnsea",
    "linkedin": null,
    "status": "emeriti"
  },
  "astacy": {
    "name": "Aaron Stacy",
    "avatar": "https://pbs.twimg.com/profile_images/3281266042/5069b845017701c465760d25ba54b83c_400x400.jpeg",
    "email": null,
    "homepage": null,
    "twitter": "aaronj1335",
    "github": "aaronj1335",
    "linkedin": null,
    "status": "emeriti"
  },
  "alevine": {
    "name": "Andrew Levine",
    "avatar": "https://pbs.twimg.com/profile_images/950842904771284992/pZwj7Nim_400x400.jpg",
    "email": null,
    "homepage": null,
    "twitter": "drewml",
    "github": "drewml",
    "linkedin": null,
    "status": "emeriti"
  },
  "kkipp": {
    "name": "Kevin Kipp",
    "avatar": "https://pbs.twimg.com/profile_images/931552869915926528/sBpw-pNh_400x400.jpg",
    "email": "kevin.kipp@gmail.com",
    "homepage": null,
    "twitter": "kevin_kipp",
    "github": "third774",
    "linkedin": null,
    "status": "active"
  },
  "pcostanzo": {
    "name": "Patrick Costanzo",
    "avatar": "https://pbs.twimg.com/profile_images/1230181384641183747/SKvgTCZL_400x400.jpg",
    "email": "costanzo.patrick@gmail.com",
    "homepage": null,
    "twitter": "pcostanz",
    "github": "pcostanz",
    "linkedin": null,
    "status": "emeriti"
  },
  "sstedman": {
    "name": "Steve Stedman",
    "avatar": "https://avatars3.githubusercontent.com/u/183122?s=460&v=4",
    "email": "steve@stedman.dev",
    "homepage": null,
    "twitter": "stedman",
    "github": "stedman",
    "linkedin": "sstedman",
    "status": "support"
  },
  "fguest": {
    "name": "Fred Guest",
    "avatar": "https://secure.meetupstatic.com/photos/member/d/6/2/9/highres_307794825.jpeg",
    "email": "fredguest@mac.com",
    "homepage": null,
    "twitter": null,
    "github": null,
    "linkedin": null,
    "status": "emeriti"
  },
  "joahg": {
    "name": "Joah Gerstenberg",
    "avatar": "https://pbs.twimg.com/profile_images/1686379255511605248/3EShXjxq_400x400.jpg",
    "email": "me@joahg.com",
    "homepage": "https://joahg.com",
    "twitter": null,
    "github": "joahg",
    "linkedin": "joahg",
    "status": "active"
  },
  "srozier": {
    "name": "Suzanne Rozier",
    "avatar": "https://avatars.githubusercontent.com/u/2723066?v=4",
    "email": null,
    "homepage": null,
    "twitter": null,
    "github": "suzubara",
    "linkedin": null,
    "status": "active"
  }
}
